celery_sqlalchemy_scheduler/__init__.py
celery_sqlalchemy_scheduler/literals.py
celery_sqlalchemy_scheduler/models.py
celery_sqlalchemy_scheduler/schedulers.py
celery_sqlalchemy_scheduler/session.py
celery_sqlalchemy_scheduler/tzcrontab.py
celery_sqlalchemy_scheduler-0.3.0.dist-info/LICENSE
celery_sqlalchemy_scheduler-0.3.0.dist-info/METADATA
celery_sqlalchemy_scheduler-0.3.0.dist-info/WHEEL
celery_sqlalchemy_scheduler-0.3.0.dist-info/top_level.txt
celery_sqlalchemy_scheduler-0.3.0.dist-info/RECORD
