Metadata-Version: 2.1
Name: celery-sqlalchemy-scheduler
Version: 0.3.0
Summary: A Scheduler Based SQLalchemy For Celery
Home-page: https://github.com/AngelLiang/celery-sqlalchemy-scheduler
Author: AngelLiang
Author-email: yannanxiu@126.com
License: MIT
Requires-Dist: celery (>=4.2)
Requires-Dist: sqlalchemy
